binascii.py
setup.py
micropython_binascii.egg-info/PKG-INFO
micropython_binascii.egg-info/SOURCES.txt
micropython_binascii.egg-info/dependency_links.txt
micropython_binascii.egg-info/top_level.txt