Metadata-Version: 1.0
Name: micropython-binascii
Version: 2.4.0-1
Summary: PyPy binascii module ported to MicroPython
Home-page: https://github.com/micropython/micropython/issues/405
Author: MicroPython Developers
Author-email: micro-python@googlegroups.com
License: MIT
Platform: UNKNOWN
